pret/ui/joy/__init__.py
pret/ui/joy/js-extension/package.json
pret/ui/joy/js-extension/schemas/pret-joy/package.json.orig
pret/ui/joy/js-extension/static/214.efaa94ddefa3978771e5.js
pret/ui/joy/js-extension/static/293.2f683412fdbfb557b232.js
pret/ui/joy/js-extension/static/293.2f683412fdbfb557b232.js.LICENSE.txt
pret/ui/joy/js-extension/static/339.76ae9b20fc15adbf94a7.js
pret/ui/joy/js-extension/static/436.ed53338b8dc4b0e5ba6e.js
pret/ui/joy/js-extension/static/436.ed53338b8dc4b0e5ba6e.js.LICENSE.txt
pret/ui/joy/js-extension/static/533.77b0e946ae6c7fd0e628.js
pret/ui/joy/js-extension/static/611.71a838c81b6d20c658f5.js
pret/ui/joy/js-extension/static/611.71a838c81b6d20c658f5.js.LICENSE.txt
pret/ui/joy/js-extension/static/666.8306911d1e0834711dfb.js
pret/ui/joy/js-extension/static/674.ca9682ddd89856cbc427.js
pret/ui/joy/js-extension/static/674.ca9682ddd89856cbc427.js.LICENSE.txt
pret/ui/joy/js-extension/static/859.c4c2ae56a05af807facb.js
pret/ui/joy/js-extension/static/remoteEntry.9f4ed9b14112fb78e9ea.js
pret/ui/joy/js-extension/static/style.js
pret/ui/joy/js-extension/static/third-party-licenses.json
pret_joy-5.0.0b52.data/data/share/jupyter/labextensions/pret-joy/package.json
pret_joy-5.0.0b52.data/data/share/jupyter/labextensions/pret-joy/schemas/pret-joy/package.json.orig
pret_joy-5.0.0b52.data/data/share/jupyter/labextensions/pret-joy/static/214.efaa94ddefa3978771e5.js
pret_joy-5.0.0b52.data/data/share/jupyter/labextensions/pret-joy/static/293.2f683412fdbfb557b232.js
pret_joy-5.0.0b52.data/data/share/jupyter/labextensions/pret-joy/static/293.2f683412fdbfb557b232.js.LICENSE.txt
pret_joy-5.0.0b52.data/data/share/jupyter/labextensions/pret-joy/static/339.76ae9b20fc15adbf94a7.js
pret_joy-5.0.0b52.data/data/share/jupyter/labextensions/pret-joy/static/436.ed53338b8dc4b0e5ba6e.js
pret_joy-5.0.0b52.data/data/share/jupyter/labextensions/pret-joy/static/436.ed53338b8dc4b0e5ba6e.js.LICENSE.txt
pret_joy-5.0.0b52.dist-info/METADATA
pret_joy-5.0.0b52.dist-info/WHEEL
pret_joy-5.0.0b52.dist-info/licenses/LICENSE
pret_joy-5.0.0b52.dist-info/RECORD
